mvw/__init__.py
mvw/api.py
mvw/config.py
mvw/database.py
mvw/display.py
mvw/main.py
mvw/menu.py
mvw/moai.py
mvw/movie.py
mvw/path.py
mvw/theme.py
mvw/renderers/__init__.py
mvw/renderers/ascii.py
mvw/renderers/base.py
mvw/renderers/block.py
mvw/renderers/pixel.py
mvw-0.5.3.dist-info/METADATA
mvw-0.5.3.dist-info/WHEEL
mvw-0.5.3.dist-info/entry_points.txt
mvw-0.5.3.dist-info/licenses/LICENSE
mvw-0.5.3.dist-info/RECORD
