Metadata-Version: 2.4
Name: mvw
Version: 0.5.3
Summary: CLI commands to catalogue all your movie reviews
Project-URL: Homepage, https://github.com/fatinul/mvw
Project-URL: Repository, https://github.com/fatinul/mvw
Project-URL: Changelog, https://github.com/fatinul/mvw/releases
Author-email: Fatinul <fatinulhaziq22@gmail.com>
Maintainer-email: Fatinul <fatinulhaziq22@gmail.com>
License: GPL-3.0-or-later
License-File: LICENSE
Keywords: catalogue,cinema,cli,movie,omdb,reviews,terminal
Classifier: Development Status :: 3 - Alpha
Classifier: Environment :: Console
Classifier: Intended Audience :: End Users/Desktop
Classifier: License :: OSI Approved :: GNU General Public License v3 or later (GPLv3+)
Classifier: Programming Language :: Python :: 3.12
Classifier: Topic :: Terminals
Requires-Python: >=3.12
Requires-Dist: asciify-them>=1.1.0
Requires-Dist: bs4>=0.0.2
Requires-Dist: iterfzf>=1.8.0.62.0
Requires-Dist: numpy>=1.24.0
Requires-Dist: pillow>=10.0.0
Requires-Dist: platformdirs>=4.5.1
Requires-Dist: requests>=2.32.5
Requires-Dist: rich-pixels>=3.0.1
Requires-Dist: rich>=14.2.0
Requires-Dist: typer>=0.21.0
